hw4/alu.v
`timescale 1ps/1ps

module alu(
    input [7:0] a,b,
    input [2:0] F,
    output [7:0] Q,
    output Cout
);

    assign Q = (F == 000) ? a+b :
        (F == 001) ? a-b :
        (F == 010) ? a|b :
        (F == 011) ? a&b :
        (F == 100) ? a^b :
        (F == 101) ? !a :
        (F == 110) ? a << 1 :
        (F == 111) ? a >> 1 : 49;
    
    /*
    assign {Cout,Q} = (F == 000) ? a+b :
        (F == 001) ? a-b :
        (F == 010) ? {1'b0,a|b} :
        (F == 011) ? {1'b0,a&b} :
        (F == 100) ? {1'b0,a^b} :
        (F == 101) ? {1'b0,!a} :
        (F == 110) ? {1'b0,a} << 1 :
        (F == 111) ? {1'b0,a} >> 1 : 0;
        */
endmodule

hw4/alu_tb.v
`timescale 1ps/1ps

module alu_tb;
    reg [7:0] a,b;
    reg [2:0] F;
    wire [7:0] Q;
    wire Cout;

    alu myalu(a,b,F,Q,Cout);
    
    always
    begin
        $dumpfile("alu.vcd");
        $dumpvars(0,alu_tb);

        a = 3;
        b = 5;
        F = 0;
        #10
        F = 1;
        #10
        a = 6;
        #10
        F = 2;
        #10
        F = 3;
        #10
        F = 4;
        #10
        F = 5;
        #10
        F = 6;
        #10
        F = 7;
        #10
        $finish;
    end
endmodule

hw4/alu.vcd
$date
	Thu Nov 14 03:27:38 2024
$end
$version
	Icarus Verilog
$end
$timescale
	1ps
$end
$scope module alu_tb $end
$var wire 1 ! Cout $end
$var wire 8 " Q [7:0] $end
$var reg 3 # F [2:0] $end
$var reg 8 $ a [7:0] $end
$var reg 8 % b [7:0] $end
$scope module myalu $end
$var wire 1 ! Cout $end
$var wire 3 & F [2:0] $end
$var wire 8 ' a [7:0] $end
$var wire 8 ( b [7:0] $end
$var wire 8 ) Q [7:0] $end
$upscope $end
$upscope $end
$enddefinitions $end
$comment Show the parameter values. $end
$dumpall
$end
#0
$dumpvars
b1000 )
b101 (
b11 '
b0 &
b101 %
b11 $
b0 #
b1000 "
z!
$end
#10
b11111110 "
b11111110 )
b1 #
b1 &
#20
b1 "
b1 )
b110 $
b110 '
#30
b110001 "
b110001 )
b10 #
b10 &
#40
b11 #
b11 &
#50
b100 #
b100 &
#60
b101 #
b101 &
#70
b110 #
b110 &
#80
b111 #
b111 &
