hw4/alu.v
`timescale 1ps/1ps

module alu(
    input [7:0] a,b,
    input [2:0] F,
    output [7:0] Q,
    output Cout
);


    assign {Cout,Q} = (F == 3'b000) ? a+b :
        (F == 3'b001) ? a-b :
        (F == 3'b010) ? {1'bx,a|b} :
        (F == 3'b011) ? {1'bx,a&b} :
        (F == 3'b100) ? {1'bx,a^b} :
        (F == 3'b101) ? {1'bx,~a} :
        (F == 3'b110) ? {1'bx,a} << 1 :
        (F == 3'b111) ? a >> 1 : 0;
    
    // assign {Cout,Q} = (F == 3'b000) ? a+b :
    //     (F == 3'b001) ? a-b :
    //     (F == 3'b010) ? a|b :
    //     (F == 3'b011) ? a&b :
    //     (F == 3'b100) ? a^b :
    //     (F == 3'b101) ? ~a :
    //     (F == 3'b110) ? a << 1 :
    //     (F == 3'b111) ? a >> 1 : 0;
    
    // assign {Cout,Q} = (F == 3'b000) ? a+b :
    //     (F == 3'b001) ? a-b :
    //     (F == 3'b010) ? {1'b0,a|b} :
    //     (F == 3'b011) ? {1'b0,a&b} :
    //     (F == 3'b100) ? {1'b0,a^b} :
    //     (F == 3'b101) ? {1'b0,~a} :
    //     (F == 3'b110) ? {1'b0,a} << 1 :
    //     (F == 3'b111) ? {1'b0,a} >> 1 : 0;

endmodule

hw4/alu_tb.v
`timescale 1ps/1ps

module alu_tb;
    reg [7:0] a,b;
    reg [2:0] F;
    wire [7:0] Q;
    wire Cout;

    alu myalu(a,b,F,Q,Cout);
    
    always
    begin
        $dumpfile("alu.vcd");
        $dumpvars(0,alu_tb);

        a = 3;
        b = 5;
        F = 0;
        #10
        F = 1;
        #10
        a = 6;
        #10
        F = 2;
        #10
        F = 3;
        #10
        F = 4;
        #10
        F = 5;
        #10
        F = 6;
        #10
        F = 7;
        #10
        F = 0;
        #10
        $finish;
    end
endmodule

hw4/alu.vcd
$date
	Thu Nov 14 03:59:13 2024
$end
$version
	Icarus Verilog
$end
$timescale
	1ps
$end
$scope module alu_tb $end
$var wire 8 ! Q [7:0] $end
$var wire 1 " Cout $end
$var reg 3 # F [2:0] $end
$var reg 8 $ a [7:0] $end
$var reg 8 % b [7:0] $end
$scope module myalu $end
$var wire 3 & F [2:0] $end
$var wire 8 ' a [7:0] $end
$var wire 8 ( b [7:0] $end
$var wire 8 ) Q [7:0] $end
$var wire 1 " Cout $end
$upscope $end
$upscope $end
$enddefinitions $end
$comment Show the parameter values. $end
$dumpall
$end
#0
$dumpvars
b1000 )
b101 (
b11 '
b0 &
b101 %
b11 $
b0 #
0"
b1000 !
$end
#10
b11111110 !
b11111110 )
1"
b1 #
b1 &
#20
b1 !
b1 )
0"
b110 $
b110 '
#30
b111 !
b111 )
x"
b10 #
b10 &
#40
b100 !
b100 )
b11 #
b11 &
#50
b11 !
b11 )
b100 #
b100 &
#60
b11111001 !
b11111001 )
b101 #
b101 &
#70
b1100 !
b1100 )
0"
b110 #
b110 &
#80
b11 !
b11 )
b111 #
b111 &
#90
b1011 !
b1011 )
b0 #
b0 &
