hw4/alu.v
`timescale 1ps/1ps

module alu(
    input [7:0] a,b,
    input [2:0] F,
    output [7:0] Q,
    output Cout
);

    assign {Cout,Q} = (F == 3'b000) ? a+b :
        (F == 3'b001) ? a-b :
        (F == 3'b010) ? {1'bx,a|b} :
        (F == 3'b011) ? {1'bx,a&b} :
        (F == 3'b100) ? {1'bx,a^b} :
        (F == 3'b101) ? {1'bx,~a} :
        (F == 3'b110) ? {1'bx,a} << 1 :
        (F == 3'b111) ? a >> 1 : 0;

endmodule

hw4/alu_tb.v
`timescale 1ns/10ps

module alu_tb;
    reg [7:0] a,b;
    reg [2:0] F;
    wire [7:0] Q;
    wire Cout;

    alu myalu(a,b,F,Q,Cout);
    
    always
    begin
        $dumpfile("alu.vcd");
        $dumpvars(0,alu_tb);

        a = 3;
        b = 5;
        F = 0;
        #10
        a = 250;
        b = 6;
        #10
        F = 1;
        #10
        a = 6;
        b = 250;
        #10
        F = 2;
        #10
        F = 3;
        #10
        F = 4;
        #10
        F = 5;
        #10
        F = 6;
        #10
        F = 7;
        #10

        $finish;
    end
endmodule

hw4/alu.vcd
$date
    Nov 14, 2024  04:33:35
$end
$version
    TOOL:	xmsim(64)	18.09-s011
$end
$timescale
    1 ps
$end

$scope module alu_tb $end
$var reg       8 !    a [7:0] $end
$var reg       8 "    b [7:0] $end
$var reg       3 #    F [2:0] $end
$var wire      8 $    Q [7:0] $end
$var wire      1 %    Cout  $end

$scope module myalu $end
$var wire      8 &    a [7:0] $end
$var wire      8 '    b [7:0] $end
$var wire      3 (    F [2:0] $end
$var wire      8 $    Q [7:0] $end
$var wire      1 %    Cout  $end
$upscope $end

$upscope $end

$enddefinitions $end
$dumpvars
b11 !
b101 "
b0 #
b1000 $
0%
b11 &
b101 '
b0 (
$end
#10
b11111010 !
b110 "
b110 '
b11111010 &
1%
b0 $
#20
b1 #
b1 (
0%
b11110100 $
#30
b110 !
b11111010 "
b11111010 '
b110 &
1%
b1100 $
#40
b10 #
b10 (
x%
b11111110 $
#50
b11 #
b11 (
b10 $
#60
b100 #
b100 (
b11111100 $
#70
b101 #
b101 (
b11111001 $
#80
b110 #
b110 (
0%
b1100 $
#90
b111 #
b111 (
b11 $
