hw3/p1.v
`timescale 1ps/1ps

module p1(A0,A1,EN,Y0,Y1,Y2,Y3);
    input A0,A1,EN;
    output Y0,Y1,Y2,Y3;

    assign Y0 = ~A0&~A1&EN;
    assign Y1 = A0&~A1&EN;
    assign Y2 = ~A0&A1&EN;
    assign Y3 = A0&A1&EN;
endmodule

hw3/p1_tb.v
`timescale 1ps/1ps

module p1_tb;
    reg A0,A1,EN;
    wire Y0,Y1,Y2,Y3;

    p1 test(A0,A1,EN,Y0,Y1,Y2,Y3);

    always
    begin
        $dumpfile("p1.vcd");
        $dumpvars(0,p1_tb);

        A0 = 0;
        A1 = 0;
        EN = 0;
        #10
        A0 = 0;
        A1 = 0;
        EN = 1;
        #10
        A0 = 0;
        A1 = 1;
        EN = 0;
        #10
        A0 = 0;
        A1 = 1;
        EN = 1;
        #10
        A0 = 1;
        A1 = 0;
        EN = 0;
        #10
        A0 = 1;
        A1 = 0;
        EN = 1;
        #10
        A0 = 1;
        A1 = 1;
        EN = 0;
        #10
        A0 = 1;
        A1 = 1;
        EN = 1;
        #10
        $finish;
    end
endmodule

hw3/p1.vcd
$date
	Fri Nov 01 18:30:38 2024
$end
$version
	Icarus Verilog
$end
$timescale
	1ps
$end
$scope module p1_tb $end
$var wire 1 ! Y3 $end
$var wire 1 " Y2 $end
$var wire 1 # Y1 $end
$var wire 1 $ Y0 $end
$var reg 1 % A0 $end
$var reg 1 & A1 $end
$var reg 1 ' EN $end
$scope module test $end
$var wire 1 % A0 $end
$var wire 1 & A1 $end
$var wire 1 ' EN $end
$var wire 1 $ Y0 $end
$var wire 1 # Y1 $end
$var wire 1 " Y2 $end
$var wire 1 ! Y3 $end
$upscope $end
$upscope $end
$enddefinitions $end
$comment Show the parameter values. $end
$dumpall
$end
#0
$dumpvars
0'
0&
0%
0$
0#
0"
0!
$end
#10
1$
1'
#20
0$
0'
1&
#30
1"
1'
#40
0"
0'
0&
1%
#50
1#
1'
#60
0#
0'
1&
#70
1!
1'
