hw3/p5.v
`timescale 1ps/1ps

module p5(
    input [2:0] a,
    input [2:0] b,
    output [5:0] f
);


    wire [2:0] s1;
    wire [2:0] s2;
    wire [3:0] p1;

    wire [2:0] s3;
    wire [3:0] p2;

    assign s1 = {a[2]&b[0], a[1]&b[0], a[0]&b[0]};
    assign s2 = {a[2]&b[1], a[1]&b[1], a[0]&b[1]};
    assign p1 = s2+s1[2:1];

    assign s3 = {a[2]&b[2], a[1]&b[2], a[0]&b[2]};
    assign p2 = s3+p1[3:1];
    
    assign f = {p2,p1[0],s1[0]};


endmodule

hw3/p5_tb.v
`timescale 1ps/1ps

module p5_tb;
    reg [2:0] a;
    reg [2:0] b;
    wire [5:0] f;

    p5 mult(a,b,f);

    always
    begin
        $dumpfile("p5.vcd");
        $dumpvars(0,p5_tb);

        a = 0;
        b = 0;
        #10
        b = 1;
        #10
        b = 2;
        #10
        b = 3;
        #10
        b = 4;
        #10
        b = 5;
        #10
        b = 6;
        #10
        b = 7;
        #10

        a = 1;
        b = 0;
        #10
        b = 1;
        #10
        b = 2;
        #10
        b = 3;
        #10
        b = 4;
        #10
        b = 5;
        #10
        b = 6;
        #10
        b = 7;
        #10

        a = 2;
        b = 0;
        #10
        b = 1;
        #10
        b = 2;
        #10
        b = 3;
        #10
        b = 4;
        #10
        b = 5;
        #10
        b = 6;
        #10
        b = 7;
        #10

        a = 3;
        b = 0;
        #10
        b = 1;
        #10
        b = 2;
        #10
        b = 3;
        #10
        b = 4;
        #10
        b = 5;
        #10
        b = 6;
        #10
        b = 7;
        #10

        a = 4;
        b = 0;
        #10
        b = 1;
        #10
        b = 2;
        #10
        b = 3;
        #10
        b = 4;
        #10
        b = 5;
        #10
        b = 6;
        #10
        b = 7;
        #10

        a = 5;
        b = 0;
        #10
        b = 1;
        #10
        b = 2;
        #10
        b = 3;
        #10
        b = 4;
        #10
        b = 5;
        #10
        b = 6;
        #10
        b = 7;
        #10

        a = 6;
        b = 0;
        #10
        b = 1;
        #10
        b = 2;
        #10
        b = 3;
        #10
        b = 4;
        #10
        b = 5;
        #10
        b = 6;
        #10
        b = 7;
        #10

        a = 7;
        b = 0;
        #10
        b = 1;
        #10
        b = 2;
        #10
        b = 3;
        #10
        b = 4;
        #10
        b = 5;
        #10
        b = 6;
        #10
        b = 7;
        #10

        $finish;
    end
endmodule

hw3/p5.vcd
$date
	Fri Nov 01 22:53:39 2024
$end
$version
	Icarus Verilog
$end
$timescale
	1ps
$end
$scope module p5_tb $end
$var wire 6 ! f [5:0] $end
$var reg 3 " a [2:0] $end
$var reg 3 # b [2:0] $end
$scope module mult $end
$var wire 3 $ a [2:0] $end
$var wire 3 % b [2:0] $end
$var wire 3 & s3 [2:0] $end
$var wire 3 ' s2 [2:0] $end
$var wire 3 ( s1 [2:0] $end
$var wire 4 ) p2 [3:0] $end
$var wire 4 * p1 [3:0] $end
$var wire 6 + f [5:0] $end
$upscope $end
$upscope $end
$enddefinitions $end
$comment Show the parameter values. $end
$dumpall
$end
#0
$dumpvars
b0 +
b0 *
b0 )
b0 (
b0 '
b0 &
b0 %
b0 $
b0 #
b0 "
b0 !
$end
#10
b1 #
b1 %
#20
b10 #
b10 %
#30
b11 #
b11 %
#40
b100 #
b100 %
#50
b101 #
b101 %
#60
b110 #
b110 %
#70
b111 #
b111 %
#80
b0 #
b0 %
b1 "
b1 $
#90
b1 !
b1 +
b1 (
b1 #
b1 %
#100
b10 !
b10 +
b1 *
b0 (
b1 '
b10 #
b10 %
#110
b11 !
b11 +
b1 (
b11 #
b11 %
#120
b100 !
b100 +
b0 *
b1 )
b0 (
b0 '
b1 &
b100 #
b100 %
#130
b101 !
b101 +
b1 (
b101 #
b101 %
#140
b110 !
b110 +
b1 *
b0 (
b1 '
b110 #
b110 %
#150
b111 !
b111 +
b1 (
b111 #
b111 %
#160
b0 !
b0 +
b0 *
b0 )
b0 (
b0 '
b0 &
b0 #
b0 %
b10 "
b10 $
#170
b10 !
b10 +
b1 *
b10 (
b1 #
b1 %
#180
b100 !
b100 +
b1 )
b10 *
b0 (
b10 '
b10 #
b10 %
#190
b110 !
b110 +
b11 *
b10 (
b11 #
b11 %
#200
b1000 !
b1000 +
b0 *
b10 )
b0 (
b0 '
b10 &
b100 #
b100 %
#210
b1010 !
b1010 +
b1 *
b10 (
b101 #
b101 %
#220
b1100 !
b1100 +
b11 )
b10 *
b0 (
b10 '
b110 #
b110 %
#230
b1110 !
b1110 +
b11 *
b10 (
b111 #
b111 %
#240
b0 !
b0 +
b0 *
b0 )
b0 (
b0 '
b0 &
b0 #
b0 %
b11 "
b11 $
#250
b1 *
b11 !
b11 +
b11 (
b1 #
b1 %
#260
b1 )
b110 !
b110 +
b11 *
b0 (
b11 '
b10 #
b10 %
#270
b10 )
b100 *
b1001 !
b1001 +
b11 (
b11 #
b11 %
#280
b1100 !
b1100 +
b0 *
b11 )
b0 (
b0 '
b11 &
b100 #
b100 %
#290
b1 *
b1111 !
b1111 +
b11 (
b101 #
b101 %
#300
b100 )
b10010 !
b10010 +
b11 *
b0 (
b11 '
b110 #
b110 %
#310
b101 )
b100 *
b10101 !
b10101 +
b11 (
b111 #
b111 %
#320
b0 !
b0 +
b0 *
b0 )
b0 (
b0 '
b0 &
b0 #
b0 %
b100 "
b100 $
#330
b100 !
b100 +
b1 )
b10 *
b100 (
b1 #
b1 %
#340
b1000 !
b1000 +
b10 )
b100 *
b0 (
b100 '
b10 #
b10 %
#350
b1100 !
b1100 +
b11 )
b110 *
b100 (
b11 #
b11 %
#360
b10000 !
b10000 +
b0 *
b100 )
b0 (
b0 '
b100 &
b100 #
b100 %
#370
b10100 !
b10100 +
b101 )
b10 *
b100 (
b101 #
b101 %
#380
b11000 !
b11000 +
b110 )
b100 *
b0 (
b100 '
b110 #
b110 %
#390
b11100 !
b11100 +
b111 )
b110 *
b100 (
b111 #
b111 %
#400
b0 !
b0 +
b0 *
b0 )
b0 (
b0 '
b0 &
b0 #
b0 %
b101 "
b101 $
#410
b1 )
b10 *
b101 !
b101 +
b101 (
b1 #
b1 %
#420
b10 )
b1010 !
b1010 +
b101 *
b0 (
b101 '
b10 #
b10 %
#430
b11 )
b111 *
b1111 !
b1111 +
b101 (
b11 #
b11 %
#440
b10100 !
b10100 +
b0 *
b101 )
b0 (
b0 '
b101 &
b100 #
b100 %
#450
b110 )
b10 *
b11001 !
b11001 +
b101 (
b101 #
b101 %
#460
b111 )
b11110 !
b11110 +
b101 *
b0 (
b101 '
b110 #
b110 %
#470
b1000 )
b111 *
b100011 !
b100011 +
b101 (
b111 #
b111 %
#480
b0 !
b0 +
b0 *
b0 )
b0 (
b0 '
b0 &
b0 #
b0 %
b110 "
b110 $
#490
b1 )
b110 !
b110 +
b11 *
b110 (
b1 #
b1 %
#500
b1100 !
b1100 +
b11 )
b110 *
b0 (
b110 '
b10 #
b10 %
#510
b100 )
b10010 !
b10010 +
b1001 *
b110 (
b11 #
b11 %
#520
b11000 !
b11000 +
b0 *
b110 )
b0 (
b0 '
b110 &
b100 #
b100 %
#530
b111 )
b11110 !
b11110 +
b11 *
b110 (
b101 #
b101 %
#540
b100100 !
b100100 +
b1001 )
b110 *
b0 (
b110 '
b110 #
b110 %
#550
b1010 )
b101010 !
b101010 +
b1001 *
b110 (
b111 #
b111 %
#560
b0 !
b0 +
b0 *
b0 )
b0 (
b0 '
b0 &
b0 #
b0 %
b111 "
b111 $
#570
b1 )
b11 *
b111 !
b111 +
b111 (
b1 #
b1 %
#580
b11 )
b1110 !
b1110 +
b111 *
b0 (
b111 '
b10 #
b10 %
#590
b101 )
b1010 *
b10101 !
b10101 +
b111 (
b11 #
b11 %
#600
b11100 !
b11100 +
b0 *
b111 )
b0 (
b0 '
b111 &
b100 #
b100 %
#610
b1000 )
b11 *
b100011 !
b100011 +
b111 (
b101 #
b101 %
#620
b1010 )
b101010 !
b101010 +
b111 *
b0 (
b111 '
b110 #
b110 %
#630
b1100 )
b1010 *
b110001 !
b110001 +
b111 (
b111 #
b111 %
