practice_code/p2_rtl.v
`timescale 1ps/1ps

module p2_rtl(A,B,C,F);
    input A,B,C;
    output F;

    assign F = (~A&B)|(A&C);
endmodule

practice_code/p2_rtl_tb.v
`timescale 1ps/1ps

module p2_rtl_tb;
    reg A,B,C;
    wire F;

    p2_rtl initial1(A,B,C,F);

    always
    begin
        $dumpfile("p2_rtl.vcd");
        $dumpvars(0,p2_rtl_tb);

        A = 0;
        B = 0;
        C = 0;
        #10
        B = 1;
        #10
        A = 1;
        #10
        B = 0;
        #10
        A = 0;
        C = 1;
        #10
        B = 1;
        #10
        A = 1;
        #10
        B = 0;
        #10
        $finish;
    end
endmodule

practice_code/p2_rtl.vcd
$date
	Mon Oct 21 23:48:34 2024
$end
$version
	Icarus Verilog
$end
$timescale
	1ps
$end
$scope module p2_rtl_tb $end
$var wire 1 ! F $end
$var reg 1 " A $end
$var reg 1 # B $end
$var reg 1 $ C $end
$scope module initial1 $end
$var wire 1 " A $end
$var wire 1 # B $end
$var wire 1 $ C $end
$var wire 1 ! F $end
$upscope $end
$upscope $end
$enddefinitions $end
$comment Show the parameter values. $end
$dumpall
$end
#0
$dumpvars
0$
0#
0"
0!
$end
#10
1!
1#
#20
0!
1"
#30
0#
#40
1$
0"
#50
1!
1#
#60
1"
#70
0#
