practice_code/p2_struct.v
`timescale 1ns/10ps

module P2(A,B,C,F);
    input A,B,C;
    output F;

    wire g1, g2, g3;

    not(g1,A);
    and(g2,g1,B);
    and(g3,A,C);
    or(F,g2,g3);
endmodule

practice_code/p2_struct_TB.v
`timescale 1ns/10ps

module p2_struct_tb;
    reg A,B,C;
    wire F;

    P2 instance1 (A,B,C,F);

    initial 
        begin
            $dumpfile("p2_struct.vcd");
            $dumpvars(0,p2_struct_tb);

            assign A = 0;
            assign B = 0;
            assign C = 0;
            #10
            assign B = 1;
            #10
            assign A = 1;
            #10
            assign B = 0;
            #10
            assign A = 0;
            assign C = 1;
            #10
            assign B = 1;
            #10
            assign A = 1;
            #10
            assign B = 0;
            #10
            $finish;
        end
endmodule

practice_code/p2_struct.vcd
$date
	Mon Oct 21 23:49:31 2024
$end
$version
	Icarus Verilog
$end
$timescale
	10ps
$end
$scope module p2_struct_tb $end
$var wire 1 ! F $end
$var reg 1 " A $end
$var reg 1 # B $end
$var reg 1 $ C $end
$scope module instance1 $end
$var wire 1 " A $end
$var wire 1 # B $end
$var wire 1 $ C $end
$var wire 1 ! F $end
$var wire 1 % g1 $end
$var wire 1 & g2 $end
$var wire 1 ' g3 $end
$upscope $end
$upscope $end
$enddefinitions $end
$comment Show the parameter values. $end
$dumpall
$end
#0
$dumpvars
0'
0&
1%
0$
0#
0"
0!
$end
#1000
1!
1&
1#
#2000
0!
0&
0%
1"
#3000
0#
#4000
1%
1$
0"
#5000
1!
1&
1#
#6000
0&
0%
1'
1"
#7000
0#
