hw5/mac.v
`timescale 1ns/1ps

module mac(
    input signed [3:0] IN,W, //should be signed
    input clk, rstb,
    output reg signed [11:0] OUT //should be signed
);

reg signed [6:0] A; //should be signed
reg signed [10:0] B; //should be signed
reg [3:0] counter;

always @(posedge clk or negedge rstb) begin

    if(~rstb) begin
        counter <= 0;
        OUT <= 0;
        B <= 0;
        A <= 0;
    end else if(counter == 9) begin
        counter <= 0;
        OUT <= B;
        B <= 0;
        A <= IN*W;
    end else if(counter < 9) begin
        counter <= counter + 1;
        A <= IN*W;
        B <= A+B;
    end else begin
        counter <= 0;
        OUT <= 0;
        B <= 0;
        A <= 0;
    end

end

endmodule

hw5/mac_tb.v
`timescale 1ns/1ps

module mac_tb;

    reg signed [3:0] IN,W; //should be signed
    reg clk, rstb;
    wire signed [11:0] OUT; //should be signed

    mac mymac(IN,W,clk,rstb,OUT);

    always begin
        $dumpfile("mac.vcd");
        $dumpvars(0,mac_tb);

        IN = 3;
        W = 2;
        clk = 1;
        rstb = 1;
        #0.5
        IN = 6;
        W = 2;
        clk = 0;
        rstb = 1;
        #0.5
        clk = 1;
        #0.5
        clk = 0;
        #0.5
        clk = 1;
        #0.5
        clk = 0;
        #0.5
        clk = 1;
        #0.5
        clk = 0;
        W = 4;
        #0.5
        clk = 1;
        #0.5
        clk = 0;
        #0.5
        clk = 1;
        #0.5
        clk = 0;
        #0.5
        clk = 1;
        #0.5
        clk = 0;
        #0.5
        clk = 1;
        #0.5
        clk = 0;
        #0.5
        clk = 1;
        #0.5
        clk = 0;
        #0.5
        clk = 1;
        #0.5
        clk = 0;
        #0.5
        clk = 1;
        #0.5
        clk = 0;
        #0.5
        clk = 1;
        #0.5
        clk = 0;
        #0.5
        clk = 1;
        #0.5
        clk = 0;
        rstb = 0;
        #0.5
        clk = 1;
        rstb = 1;
        #0.5
        clk = 0;
        #0.5
        clk = 1;
        #0.5
        clk = 0;
        #0.5
        clk = 1;
        #0.5
        $finish;
    end

endmodule

hw5/mac.vcd
$date
	Thu Dec 05 07:09:55 2024
$end
$version
	Icarus Verilog
$end
$timescale
	1ps
$end
$scope module mac_tb $end
$var wire 12 ! OUT [11:0] $end
$var reg 4 " IN [3:0] $end
$var reg 4 # W [3:0] $end
$var reg 1 $ clk $end
$var reg 1 % rstb $end
$scope module mymac $end
$var wire 4 & IN [3:0] $end
$var wire 4 ' W [3:0] $end
$var wire 1 $ clk $end
$var wire 1 % rstb $end
$var reg 7 ( A [6:0] $end
$var reg 11 ) B [10:0] $end
$var reg 12 * OUT [11:0] $end
$var reg 4 + counter [3:0] $end
$upscope $end
$upscope $end
$enddefinitions $end
$comment Show the parameter values. $end
$dumpall
$end
#0
$dumpvars
b0 +
b0 *
b0 )
b0 (
b0 '
b0 &
1%
1$
b0 #
b0 "
b0 !
$end
#500
0$
#1000
b10 (
b1 +
b10 #
b10 '
b1 "
b1 &
1$
#1500
0$
#2000
b10 )
b1000 (
b10 +
b100 #
b100 '
b10 "
b10 &
1$
#2500
0$
#3000
b1010 )
b10010 (
b11 +
b110 #
b110 '
b11 "
b11 &
1$
#3500
0$
#4000
b11100 )
b1100000 (
b100 +
b1000 #
b1000 '
b100 "
b100 &
1$
#4500
0$
#5000
b11111111100 )
b1100010 (
b101 +
b1010 #
b1010 '
b101 "
b101 &
1$
#5500
0$
#6000
b11111011110 )
b1101000 (
b110 +
b1100 #
b1100 '
b110 "
b110 &
1$
#6500
0$
#7000
b11111000110 )
b1110010 (
b111 +
b1110 #
b1110 '
b111 "
b111 &
1$
#7500
0$
#8000
b11110111000 )
b0 (
b1000 +
b0 #
b0 '
b1000 "
b1000 &
1$
#8500
0$
#9000
b1110010 (
b1001 +
b10 #
b10 '
b1001 "
b1001 &
1$
#9500
0$
#10000
b1101000 (
b0 )
b111110111000 !
b111110111000 *
b0 +
b100 #
b100 '
b1010 "
b1010 &
1$
#10500
0$
#11000
b11111101000 )
b1100010 (
b1 +
b110 #
b110 '
b1011 "
b1011 &
1$
#11500
0$
#12000
b11111001010 )
b100000 (
b10 +
b1000 #
b1000 '
b1100 "
b1100 &
1$
#12500
0$
#13000
b11111101010 )
b10010 (
b11 +
b1010 #
b1010 '
b1101 "
b1101 &
1$
#13500
0$
#14000
b11111111100 )
b1000 (
b100 +
b1100 #
b1100 '
b1110 "
b1110 &
1$
#14500
0$
#15000
b100 )
b10 (
b101 +
b1110 #
b1110 '
b1111 "
b1111 &
1$
#15500
0$
#16000
b110 )
b0 (
b110 +
b0 #
b0 '
b0 "
b0 &
1$
#16500
0$
#17000
b10 (
b111 +
b10 #
b10 '
b1 "
b1 &
1$
#17500
0$
#18000
b1000 )
b1000 (
b1000 +
b100 #
b100 '
b10 "
b10 &
1$
#18500
0$
#19000
b10000 )
b10010 (
b1001 +
b110 #
b110 '
b11 "
b11 &
1$
#19500
0$
#20000
b1100000 (
b0 )
b10000 !
b10000 *
b0 +
b1000 #
b1000 '
b100 "
b100 &
1$
#20500
0$
#21000
b11111100000 )
b1100010 (
b1 +
b1010 #
b1010 '
b101 "
b101 &
1$
